[
  // Zotzpyre
  {
    "dimension": [0,10],
    "mobs": [
      {
        "mob": "betteranimalsplus:zotzpyre",
        "weight": 2,
        "groupcountmin": 1,
        "groupcountmax": 1
      }
    ]
  },
  
  // Gold Golems
  {
    "dimension": -1,
    "block": ["betternether:bone_tile", "betternether:nether_brick_tile_large"],
    "mobs": [
      {
        "mob": "netherex:gold_golem",
        "weight": 1,
        "groupcountmin": 1,
        "groupcountmax": 1
      }
    ]
  },

  // Magma Monster Grunt Overworld
  {
    "dimension": 0,
    "mobs": [
      {
        "mob": "magma_monsters:magma_monster_grunt",
        "weight": 1,
        "groupcountmin": 1,
        "groupcountmax": 1
      }
    ]
  },

  // Magma Monster Grunt Nether
  {
    "dimension": -1,
    "mobs": [
      {
        "mob": "magma_monsters:magma_monster_grunt",
        "weight": 50,
        "groupcountmin": 1,
        "groupcountmax": 3
      }
    ]
  },

  // Magma Monster Nether
  {
    "dimension": -1,
    "mobs": [
      {
        "mob": "magma_monsters:magma_monster",
        "weight": 50,
        "groupcountmin": 1,
        "groupcountmax": 1
      }
    ]
  },

  // Cockatrice/Kelenk
  {
    "dimension": 0,
    "seesky": true,
    "mobs": [
      {
        "mob": "aether_legacy:cockatrice",
        "weight": 2
      }
    ]
  },


  // Void Eyes
  {
    "dimension": [0,1,10],
    "mobs": [
      {
        "mob": "primitivemobs:void_eye",
        "weight": 3,
        "groupcountmin": 1,
        "groupcountmax": 1
      }
    ]
  },

  // Trollagers
  {
    "dimension": [0,10],
    "mobs": [
      {
        "mob": "primitivemobs:trollager",
        "weight": 3,
        "groupcountmin": 1,
        "groupcountmax": 1
      }
    ]
  },



  // Pigmen
  {
    "dimension": -1,
    "mobs": [
      {
        "mob": "specialmobs:brutepigzombie",
        "weight": 3,
        "groupcountmin": 1,
        "groupcountmax": 3
      }
    ]
  },
  {
    "dimension": -1,
    "mobs": [
      {
        "mob": "specialmobs:hungrypigzombie",
        "weight": 3,
        "groupcountmin": 1,
        "groupcountmax": 3
      }
    ]
  },

  // Wither Skeletons
  {
    "dimension": -1,
    "mobs": [
      {
        "mob": "specialmobs:brutewitherskeleton",
        "weight": 3,
        "groupcountmin": 1,
        "groupcountmax": 1
      }
    ]
  },
  {
    "dimension": -1,
    "mobs": [
      {
        "mob": "specialmobs:giantwitherskeleton",
        "weight": 3,
        "groupcountmin": 1,
        "groupcountmax": 1
      }
    ]
  },
  {
    "dimension": -1,
    "mobs": [
      {
        "mob": "specialmobs:spitfirewitherskeleton",
        "weight": 3,
        "groupcountmin": 1,
        "groupcountmax": 1
      }
    ]
  },


  {
    "dimension": 0,
    "mobs": [
      {
        "mob": "netherex:salamander",
        "weight": 3
      }
    ]
  },


  {
    "dimension": -1,
    "mobs": [
      {
        "mob": "netherex:wight",
        "weight": 3
      }
    ]
  },
  {
    "dimension": -1,
    "mobs": [
      {
        "mob": "netherex:spore_creeper",
        "weight": 3
      }
    ]
  },






  // Creepers
  {
    "dimension": 10,
    "mobs": [
      {
        "mob": "specialmobs:deathcreeper",
        "weight": 5
      }
    ]
  },
  {
    "dimension": -1,
    "mobs": [
      {
        "mob": "specialmobs:doomcreeper",
        "weight": 3
      }
    ]
  },
  {
    "dimension": [0,10],
    "mobs": [
      {
        "mob": "primitivemobs:rocket_creeper",
        "weight": 5,
        "groupcountmin": 1,
        "groupcountmax": 1
      }
    ]
  },


  {
    "dimension": [0,10],
    "mobs": [
      {
        "mob": "specialmobs:jumpingcreeper",
        "weight": 5,
        "groupcountmin": 1,
        "groupcountmax": 1
      }
    ]
  },

  {
    "dimension": [0,10],
    "mobs": [
      {
        "mob": "specialmobs:darkcreeper",
        "weight": 5,
        "groupcountmin": 1,
        "groupcountmax": 1
      }
    ]
  },

  {
    "dimension": [0,10],
    "mobs": [
      {
        "mob": "specialmobs:lightningcreeper",
        "weight": 5,
        "groupcountmin": 1,
        "groupcountmax": 1
      }
    ]
  },

  {
    "dimension": [0,10],
    "mobs": [
      {
        "mob": "specialmobs:firecreeper",
        "weight": 5,
        "groupcountmin": 1,
        "groupcountmax": 1
      }
    ]
  },

  {
    "dimension": [0,10],
    "mobs": [
      {
        "mob": "specialmobs:endercreeper",
        "weight": 5,
        "groupcountmin": 1,
        "groupcountmax": 1
      }
    ]
  },

  {
    "dimension": [0,10],
    "mobs": [
      {
        "mob": "specialmobs:splittingcreeper",
        "weight": 5,
        "groupcountmin": 1,
        "groupcountmax": 1
      }
    ]
  },



    // Zombies
  {
    "dimension": [0,10],
    "mobs": [
      {
        "mob": "specialmobs:brutezombie",
        "weight": 5,
        "groupcountmin": 1,
        "groupcountmax": 1
      }
    ]
  },

  {
    "dimension": [0,10],
    "mobs": [
      {
        "mob": "specialmobs:hungryzombie",
        "weight": 5,
        "groupcountmin": 1,
        "groupcountmax": 1
      }
    ]
  },

  {
    "dimension": [0,10],
    "mobs": [
      {
        "mob": "specialmobs:plaguezombie",
        "weight": 5,
        "groupcountmin": 1,
        "groupcountmax": 1
      }
    ]
  },

  {
    "dimension": [0,10],
    "mobs": [
      {
        "mob": "specialmobs:fishingzombie",
        "weight": 5,
        "groupcountmin": 1,
        "groupcountmax": 1
      }
    ]
  },

  {
    "dimension": [0,10],
    "mobs": [
      {
        "mob": "specialmobs:firezombie",
        "weight": 5,
        "groupcountmin": 1,
        "groupcountmax": 1
      }
    ]
  },

  {
    "dimension": [0,10],
    "mobs": [
      {
        "mob": "specialmobs:giantzombie",
        "weight": 5,
        "groupcountmin": 1,
        "groupcountmax": 1
      }
    ]
  },



      // Skeletons
  {
    "dimension": [0,10],
    "mobs": [
      {
        "mob": "specialmobs:bruteskeleton",
        "weight": 5,
        "groupcountmin": 1,
        "groupcountmax": 1
      }
    ]
  },

  {
    "dimension": [0,10],
    "mobs": [
      {
        "mob": "specialmobs:sniperskeleton",
        "weight": 5,
        "groupcountmin": 1,
        "groupcountmax": 1
      }
    ]
  },

  {
    "dimension": [0,10],
    "mobs": [
      {
        "mob": "specialmobs:poisonskeleton",
        "weight": 5,
        "groupcountmin": 1,
        "groupcountmax": 1
      }
    ]
  },

  {
    "dimension": [0,10],
    "mobs": [
      {
        "mob": "specialmobs:ninjaskeleton",
        "weight": 5,
        "groupcountmin": 1,
        "groupcountmax": 1
      }
    ]
  },

  {
    "dimension": [0,10],
    "mobs": [
      {
        "mob": "specialmobs:fireskeleton",
        "weight": 5,
        "groupcountmin": 1,
        "groupcountmax": 1
      }
    ]
  },

  {
    "dimension": [0,10],
    "mobs": [
      {
        "mob": "specialmobs:giantskeleton",
        "weight": 5,
        "groupcountmin": 1,
        "groupcountmax": 1
      }
    ]
  },

  {
    "dimension": [0,10],
    "mobs": [
      {
        "mob": "specialmobs:spitfireskeleton",
        "weight": 5,
        "groupcountmin": 1,
        "groupcountmax": 1
      }
    ]
  },

  {
    "dimension": [0,10],
    "mobs": [
      {
        "mob": "specialmobs:gatlingskeleton",
        "weight": 5,
        "groupcountmin": 1,
        "groupcountmax": 1
      }
    ]
  },

   // Spiders
  {
    "dimension": [0,10],
    "mobs": [
      {
        "mob": "specialmobs:hungryspider",
        "weight": 5,
        "groupcountmin": 1,
        "groupcountmax": 1
      }
    ]
  },

  {
    "dimension": [0,10],
    "mobs": [
      {
        "mob": "specialmobs:palespider",
        "weight": 5,
        "groupcountmin": 1,
        "groupcountmax": 1
      }
    ]
  },

  {
    "dimension": 0,
    "mobs": [
      {
        "mob": "specialmobs:desertspider",
        "weight": 5,
        "groupcountmin": 1,
        "groupcountmax": 1
      }
    ]
  },

  {
    "dimension": [0,10],
    "mobs": [
      {
        "mob": "specialmobs:witchspider",
        "weight": 5,
        "groupcountmin": 1,
        "groupcountmax": 1
      }
    ]
  },

  {
    "dimension": [0,10],
    "mobs": [
      {
        "mob": "specialmobs:poisonspider",
        "weight": 5,
        "groupcountmin": 1,
        "groupcountmax": 1
      }
    ]
  },

  {
    "dimension": [0,10],
    "mobs": [
      {
        "mob": "specialmobs:webspider",
        "weight": 5,
        "groupcountmin": 1,
        "groupcountmax": 1
      }
    ]
  },

  {
    "dimension": [0,10],
    "mobs": [
      {
        "mob": "specialmobs:giantspider",
        "weight": 5,
        "groupcountmin": 1,
        "groupcountmax": 1
      }
    ]
  },

  {
    "dimension": [0,10],
    "mobs": [
      {
        "mob": "specialmobs:flyingspider",
        "weight": 5,
        "groupcountmin": 1,
        "groupcountmax": 1
      }
    ]
  },

  {
    "dimension": [0,10],
    "mobs": [
      {
        "mob": "specialmobs:motherspider",
        "weight": 5,
        "groupcountmin": 1,
        "groupcountmax": 1
      }
    ]
  },

  // Slimes

  {
    "dimension": 0,
    "mobs": [
      {
        "mob": "specialmobs:blackberryslime",
        "weight": 5,
        "groupcountmin": 1,
        "groupcountmax": 1
      }
    ]
  },

  {
    "dimension": 0,
    "mobs": [
      {
        "mob": "specialmobs:lemonslime",
        "weight": 5,
        "groupcountmin": 1,
        "groupcountmax": 1
      }
    ]
  },

  {
    "dimension": 0,
    "mobs": [
      {
        "mob": "specialmobs:grapeslime",
        "weight": 5,
        "groupcountmin": 1,
        "groupcountmax": 1
      }
    ]
  },

  {
    "dimension": 0,
    "mobs": [
      {
        "mob": "specialmobs:blueberryslime",
        "weight": 5,
        "groupcountmin": 1,
        "groupcountmax": 1
      }
    ]
  },

  {
    "dimension": 0,
    "mobs": [
      {
        "mob": "specialmobs:strawberryslime",
        "weight": 5,
        "groupcountmin": 1,
        "groupcountmax": 1
      }
    ]
  },

  {
    "dimension": 0,
    "mobs": [
      {
        "mob": "specialmobs:watermelonslime",
        "weight": 5,
        "groupcountmin": 1,
        "groupcountmax": 1
      }
    ]
  },






  // Enderman

  {
    "dimension": [0,10,1,-1],
    "mobs": [
      {
        "mob": "specialmobs:blindingenderman",
        "weight": 3,
        "groupcountmin": 1,
        "groupcountmax": 1
      }
    ]
  },

  {
    "dimension": [0,10,1],
    "mobs": [
      {
        "mob": "specialmobs:icyenderman",
        "weight": 3,
        "groupcountmin": 1,
        "groupcountmax": 1
      }
    ]
  },

  {
    "dimension": [0,10,1],
    "mobs": [
      {
        "mob": "specialmobs:lightningenderman",
        "weight": 3,
        "groupcountmin": 1,
        "groupcountmax": 1
      }
    ]
  },

  {
    "dimension": [0,10,1],
    "mobs": [
      {
        "mob": "specialmobs:mirageenderman",
        "weight": 3,
        "groupcountmin": 1,
        "groupcountmax": 1
      }
    ]
  },
  
  {
    "dimension": [0,10,1],
    "mobs": [
      {
        "mob": "specialmobs:blindingenderman",
        "weight": 3,
        "groupcountmin": 1,
        "groupcountmax": 1
      }
    ]
  },

// skydrake
 {
    "dimension": 4,
    "mobs": [
      {
        "mob": "mowziesmobs:naga",
        "weight": 0.5,
        "groupcountmin": 1,
        "groupcountmax": 1
      }
    ]
  },
  
 // Fish's Undead Rising 
  {
    "dimension": [0,10],
    "mobs": [
      {
        "mob": "mod_lavacow:wendigo",
        "weight": 0.5,
        "groupcountmin": 1,
        "groupcountmax": 1
      }
    ]
  },
  
  {
    "dimension": 0,
    "mobs": [
      {
        "mob": "mod_lavacow:zombiepiranha",
        "weight": 5,
        "groupcountmin": 3,
        "groupcountmax": 10
      }
    ]
  },
  
  {
    "dimension": 0,
    "mobs": [
      {
        "mob": "mod_lavacow:undeadswine",
        "weight": 1,
        "groupcountmin": 1,
        "groupcountmax": 3
      }
    ]
  },
  
    {
    "dimension": 0,
    "mobs": [
      {
        "mob": "mod_lavacow:zombiefrozen",
        "weight": 5,
        "groupcountmin": 1,
        "groupcountmax": 3
      }
    ]
  },
  
    {
    "dimension": [0,10],
    "mobs": [
      {
        "mob": "mod_lavacow:zombiemushroom",
        "weight": 2,
        "groupcountmin": 1,
        "groupcountmax": 3
      }
    ]
  },
  
    {
    "dimension": 0,
    "mobs": [
      {
        "mob": "mod_lavacow:foglet",
        "weight": 6,
        "groupcountmin": 1,
        "groupcountmax": 4
      }
    ]
  },
  
  {
    "dimension": 0,
    "mobs": [
      {
        "mob": "mod_lavacow:ptera",
        "weight": 3,
        "groupcountmin": 1,
        "groupcountmax": 4
      }
    ]
  },
  
  {
    "dimension": 4,
    "mobs": [
      {
        "mob": "mod_lavacow:ptera",
        "weight": 1,
        "groupcountmin": 2,
        "groupcountmax": 4
      }
    ]
  },  
// rats
 {
    "dimension": 0,
    "mobs": [
      {
        "mob": "rats:rat",
        "weight": 3,
        "groupcountmin": 1,
        "groupcountmax": 5
      }
    ]
  },
  
  {
    "dimension": [-1,0,10],
    "mobs": [
      {
        "mob": "rats:ratlantean_spirit",
        "weight": 5,
        "groupcountmin": 1,
        "groupcountmax": 2
      }
    ]
  },
  
  {
    "dimension": [0,10],
    "mobs": [
      {
        "mob": "rats:plague_beast",
        "weight": 3,
        "groupcountmin": 1,
        "groupcountmax": 2
      }
    ]
  },
  
  {
    "dimension": 0,
    "mobs": [
      {
        "mob": "rats:black_death",
        "weight": 0.05,
        "groupcountmin": 1,
        "groupcountmax": 1
      }
    ]
  },

  {
    "dimension": 4,
    "mobs": [
      {
        "mob": "netherex:wight",
        "weight": 3,
        "groupcountmin": 1,
        "groupcountmax": 3
      }
    ]
  },

  {
    "dimension": 4,
    "mobs": [
      {
        "mob": "netherex:coolmar_spider",
        "weight": 5,
        "groupcountmin": 1,
        "groupcountmax": 3
      }
    ]
  },
 
   {
    "dimension": 4,
    "mobs": [
      {
        "mob": "primitivemobs:harpy",
        "weight": 3,
        "groupcountmin": 1,
        "groupcountmax": 5
      }
    ]
  },
 
    {
    "dimension": 4,
    "mobs": [
      {
        "mob": "iceandfire:stymphalianbird",
        "weight": 1,
        "groupcountmin": 1,
        "groupcountmax": 5
      }
    ]
  },
 
   {
    "dimension": 0,
    "mobs": [
      {
        "mob": "mod_lavacow:vespa",
        "weight": 1,
        "groupcountmin": 1,
        "groupcountmax": 1
      }
    ]
  },
   {
    "dimension": 0,
    "mobs": [
      {
        "mob": "mod_lavacow:scarecrow",
        "weight": 2,
        "groupcountmin": 1,
        "groupcountmax": 2
      }
    ]
  }
]
