{
	"footsteps": {
		"contenttweaker:voided_rock": "bedrock",
		"contenttweaker:void_block+foliage": "fire",
		"contenttweaker:rocky_dirt": "dirt,stone",
		"contenttweaker:n_copper_sandstone": "ore",
		"contenttweaker:n_copper_sandstone_red": "ore",
		"contenttweaker:limestone_cobble": "sandstone",
		"contenttweaker:ardicite": "stone,fire",
		"contenttweaker:dormant_ardicite_onyx": "ore,fire",
		"contenttweaker:healing": "composite",
		"defiledlands:healing_pad": "composite",
		"contenttweaker:elevator": "brickstone",
		"advancedliftingmethods:ultimate_ender_elevator": "brickstone",
		"contenttweaker:charmpeat": "grass",
		"contenttweaker:raw_mythril_block": "ore",
		"contenttweaker:raw_silver_block": "ore",
		"contenttweaker:raw_copper_block": "ore",
		"contenttweaker:raw_viridium_block": "ore",
		"contenttweaker:raw_iron_block": "ore",
		"contenttweaker:raw_gold_block": "ore",
		"contenttweaker:raw_tin_block": "ore",
		"contenttweaker:raw_gravitite_block": "ore",
		"contenttweaker:halite": "ice",
		"contenttweaker:abyss_pizza_block": "organic",
		"contenttweaker:chicken_pizza_block": "organic",
		"contenttweaker:plain_pizza_block": "organic",
		"contenttweaker:yeast": "organic",
		"contenttweaker:yeast_flour": "organic",
		"contenttweaker:magicked_stone": "composite",
		"contenttweaker:dormant_onyx": "ore",
		"contenttweaker:fiery_nether_sludge": "organic",
		"contenttweaker:hardened_fiery_nether_sludge": "sandstone",
		"betterwithmods:nether_clay": "organic",
		"betterwithmods:aesthetic[blocktype=nether_clay]": "sandstone",
		"contenttweaker:charcoal_pile": "dirt",
		"contenttweaker:crucible": "dirt",
		"contenttweaker:grass_paver": "brickstone",
		"contenttweaker:farlanderexoritebrick": "marble",
		"contenttweaker:farlanderdiamondbrick": "marble",
		"contenttweaker:farlanderzanitebrick": "marble",
		"contenttweaker:witheredblock": "quicksand",
		"contenttweaker:refracotta": "sandstone",
		"contenttweaker:refracotta_black": "sandstone",
		"contenttweaker:refracotta_red": "sandstone",
		"contenttweaker:refracotta_green": "sandstone",
		"contenttweaker:refracotta_brown": "sandstone",
		"contenttweaker:refracotta_blue": "sandstone",
		"contenttweaker:refracotta_purple": "sandstone",
		"contenttweaker:refracotta_cyan": "sandstone",
		"contenttweaker:refracotta_light_gray": "sandstone",
		"contenttweaker:refracotta_gray": "sandstone",
		"contenttweaker:refracotta_pink": "sandstone",
		"contenttweaker:refracotta_lime": "sandstone",
		"contenttweaker:refracotta_yellow": "sandstone",
		"contenttweaker:refracotta_light_blue": "sandstone",
		"contenttweaker:refracotta_magenta": "sandstone",
		"contenttweaker:refracotta_orange": "sandstone",
		"contenttweaker:refracotta_white": "sandstone",
		"contenttweaker:cobblestone_path_basalt": "obsidian",
		"contenttweaker:unfired_mud_brick": "organic",
		"betterwithmods:unfired_pottery[potterytype=nether_brick]": "organic",
		"contenttweaker:unfired_fiery_brick": "organic",
		"contenttweaker:big_limestone_bricks": "sandstone",
		"contenttweaker:big_chalk_bricks": "sandstone",
		"contenttweaker:big_shale_bricks": "brickstone",
		"contenttweaker:big_siltstone_bricks": "brickstone",
		"contenttweaker:big_lignite_bricks": "brickstone",
		"contenttweaker:big_dolomite_bricks": "brickstone",
		"contenttweaker:big_greywacke_bricks": "brickstone",
		"contenttweaker:big_chert_bricks": "brickstone",
		"contenttweaker:foundation_micomi": "brickstone",
		"contenttweaker:glareshaft_small": "metalbar",
		"contenttweaker:tapestry_red": "rug",
		"contenttweaker:tapestry_purple": "rug"
	}
}