{
	"footsteps": {
		"stygian:endobsidian": "obsidian",
		"stygian:endmagma": "sandstone",
		"stygian:endgrass": "grass,stone",
		"stygian:endtallgrass+foliage": "straw",
		"stygian:endglow+foliage": "straw",
		"earthworks:block_slate_green": "brickstone,stone",
		"earthworks:block_slate_purple": "brickstone,stone",
		"earthworks:block_slate": "brickstone,stone",
		"defiledlands:gravel_defiled": "gravel",
		"minecraft:ladder": "ladder",
		"minecraft:chorus_plant": "wood",
		"minecraft:chorus_flower": "wood",
		"undergroundbiomes:igneous_overgrown": "grass,stone",
		"undergroundbiomes:metamorphic_overgrown": "grass,stone",
		"undergroundbiomes:sedimentary_overgrown": "grass,stone",
		"undergroundbiomes:igneous_overgrown_snowed": "grass,stone",
		"undergroundbiomes:metamorphic_overgrown_snowed": "grass,stone",
		"undergroundbiomes:sedimentary_overgrown_snowed": "grass,stone",
		"charm:rotten_flesh_block": "organic",
		"futuremc:campfire": "fire,stone",
		"dimstack:bedrock": "ice,obsidian,bedrock",
		"dimstack:portal": "ice,obsidian,bedrock",
		"iceandfire:chared_gravel": "gravel,sand",
		"osv:clay_deposits_dirt": "dirt",
		"osv:clay_deposits_sand": "dirt,sand",
		"osv:clay_deposits_gravel": "dirt,gravel",
		"osv:clay_deposits_biomesoplenty_dirt": "dirt",
		"osv:clay_deposits_biomesoplenty_dirt_1": "dirt",
		"osv:clay_deposits_biomesoplenty_dirt_2": "dirt",
		"osv:clay_deposits_contenttweaker_rocky_dirt": "dirt,stone",
		"undergroundbiomes:igneous_gravel": "gravel",
		"undergroundbiomes:metamorphic_gravel": "gravel",
		"undergroundbiomes:sedimentary_gravel": "gravel",
		"betterwithmods:aesthetic[blocktype=soap]": "organic",
		"betterwithaddons:wet_soap": "organic",
		"betterwithmods:aesthetic[blocktype=chopping]": "brickstone",
		"betterwithmods:aesthetic[blocktype=chopping_blood]": "brickstone,organic",
		"minecraft:bone_block": "marble",
		"netherex:bone_sliver": "marble",
		"netherex:bone_chunk": "marble",
		"minecraft:magma": "stone,fire",
		"betterwithaddons:lattice": "metalbar",
		"biomesoplenty:gem_block": "marble",
		"minecraft:diamond_block": "marble",
		"arcanearchives:storage_raw_quartz": "marble",
		"arcanearchives:storage_shaped_quartz": "marble",
		"simpleores:onyx_block": "marble",
		"netherex:nether_brick_fence_gate+bigger": "brickstone",
		"futuremc:nether_brick_wall+bigger": "brickstone",
		"simpleores:onyx_ore": "ore",
		"osv:simpleores_onyx_ore_contenttweaker_ardicite": "fire,ore",
		"dungeontactics:mithril_block": "brickstone",
		"iceandfire:myrmex_resin_sticky": "dirt,organic",
		"iceandfire:myrmex_desert_resin_block": "sandstone",
		"iceandfire:myrmex_jungle_resin_block": "stone,dirt",
		"minecraft:torch+foliage": "fire",
		"glaretorch:blockglaretorchsmall+foliage": "fire,metalbar",
		"glaretorch:blockglaretorch+foliage": "fire",
		"glaretorch:blockglaretorchlarge+foliage": "fire",
		"glaretorch:blockglaretorchlarge2+foliage": "fire",
		"inspirations:torch_lever+foliage": "fire",
		"biomesoplenty:grass[variant=overgrown_stone]": "grass,stone",
		"rats:fish_barrel[facing=up]": "wood,organic",
		"endreborn:dragon_essence": "ore",
		"biomesoplenty:bramble_plant": "wood",
		"endreborn:block_essence_ore": "bedrock",
		"undergroundbiomes:sedimentary_stone[type=chalk]": "sandstone",
		"pyrotech:anvil_granite": "brickstone",
		"pyrotech:stone_tank": "brickstone,glass",
		"pyrotech:brick_tank": "brickstone,glass",
		"pyrotech:stone_bricks": "brickstone",
		"pyrotech:refractory_brick_block": "brickstone",
		"pyrotech:tar_drain": "brickstone",
		"pyrotech:faucet_stone": "brickstone",
		"pyrotech:faucet_brick": "brickstone",
		"pyrotech:stone_door": "brickstone",
		"pyrotech:refractory_door": "brickstone",
		"pyrotech:tar_collector": "brickstone",
		"pyrotech:stone_kiln": "brickstone",
		"pyrotech:brick_kiln": "brickstone",
		"ceramics:clay_hard": "brickstone",
		"ceramics:clay_slab": "brickstone",
		"ceramics:clay_wall+bigger": "brickstone",
		"ceramics:clay_hard[type=lava_bricks]": "brickstone,fire",
		"ceramics:clay_slab[type=lava_bricks]": "brickstone,fire",
		"ceramics:clay_wall[type=lava_bricks]+bigger": "brickstone,fire",
		"ceramics:lava_bricks_stairs": "brickstone,fire",
		"ceramics:porcelain": "marble",
		"ceramics:rainbow_clay": "marble",
		"ceramics:clay_barrel": "sandstone",
		"ceramics:clay_barrel_stained": "sandstone",
		"ceramics:clay_barrel_stained_extension": "sandstone",
		"ceramics:porcelain_barrel": "marble",
		"ceramics:porcelain_barrel_extension": "marble",
		"ceramics:faucet": "marble",
		"ceramics:channel": "marble",
		"betterwithmods:blood_log": "organic,log",
		"betterwithmods:blood_leaves": "organic,leaves",
		"pyrotech:log_pile": "log",
		"iceandfire:dreadwood_log": "log",
		"pyrotech:dense_quartz_ore_large": "marble",
		"pyrotech:dense_quartz_ore_small": "marble",
		"pyrotech:dense_quartz_ore_rocks": "marble",
		"pyrotech:dense_redstone_ore_large": "composite",
		"pyrotech:dense_redstone_ore_small": "composite",
		"pyrotech:dense_redstone_ore_rocks": "composite"
	}
}